src/__init__.py
src/__main__.py
whatsapp_message_sender-0.2.3.dist-info/METADATA
whatsapp_message_sender-0.2.3.dist-info/WHEEL
whatsapp_message_sender-0.2.3.dist-info/entry_points.txt
whatsapp_message_sender-0.2.3.dist-info/top_level.txt
whatsapp_message_sender-0.2.3.dist-info/RECORD
