Metadata-Version: 2.4
Name: whatsapp_message_sender
Version: 0.2.3
Summary: A tool for sending WhatsApp messages to clients with pending payments
Requires-Dist: pandas
Requires-Dist: pyautogui
Requires-Dist: openpyxl
Dynamic: requires-dist
Dynamic: summary
